wlkc_admin/__init__.py
wlkc_admin/services/__init__.py
wlkc_admin/services/main.py
wlkc_admin/services/menu.py
wlkc_admin/services/permission.py
wlkc_admin/services/router.py
wlkc_admin/services/sysConfig.py
wlkc_admin/services/sysDept.py
wlkc_admin/services/sysDict.py
wlkc_admin/services/sysMenu.py
wlkc_admin/services/sysPost.py
wlkc_admin/services/sysRole.py
wlkc_admin/services/sysUser.py
wlkc_admin/views/__init__.py
wlkc_admin/views/configView.py
wlkc_admin/views/dictView.py
wlkc_admin/views/home.py
wlkc_admin/views/mainView.py
wlkc_admin/views/menuView.py
wlkc_admin/views/roleView.py
wlkc_admin/views/userView.py
wlkc_core/__init__.py
wlkc_core/database.py
wlkc_core/settings.py
wlkc_core/cache_modules/__init__.py
wlkc_core/exceptions/__init__.py
wlkc_core/modules/__init__.py
wlkc_core/utils/__init__.py
wlkc_core/utils/auth.py
wlkc_core/utils/imgCode.py
wlkc_core/utils/iputils.py
wlkc_core/utils/jwt.py
wlkc_core/utils/loggingHandler.py
wlkc_core/utils/operationLog.py
wlkc-0.1.2.dist-info/LICENSE
wlkc-0.1.2.dist-info/METADATA
wlkc-0.1.2.dist-info/WHEEL
wlkc-0.1.2.dist-info/top_level.txt
wlkc-0.1.2.dist-info/RECORD
