Metadata-Version: 2.1
Name: wlkc
Version: 0.1.2
Summary: A simple flask app for wlkc
Author: wlkc
Author-email: wlkc@hotmail.com
Classifier: Programming Language :: Python :: 3
Classifier: License :: OSI Approved :: MIT License
Classifier: Operating System :: OS Independent
Requires-Python: >=3.7
License-File: LICENSE
